examples/__init__.py
examples/example_usage.py
shardcast/__init__.py
shardcast/client.py
shardcast/client_node.py
shardcast/envs.py
shardcast/middle_node.py
shardcast/origin_server.py
shardcast/server.py
shardcast/utils.py
shardcast-0.3.2.dist-info/METADATA
shardcast-0.3.2.dist-info/WHEEL
shardcast-0.3.2.dist-info/entry_points.txt
shardcast-0.3.2.dist-info/top_level.txt
shardcast-0.3.2.dist-info/RECORD
