Metadata-Version: 2.4
Name: shardcast
Version: 0.3.2
Summary: A package for distributing large files via HTTP P2P network
Author: felix
Author-email: P2P Weight Transfer <felix@primeintellect.ai>
Classifier: Development Status :: 3 - Alpha
Classifier: Intended Audience :: Developers
Classifier: License :: OSI Approved :: MIT License
Classifier: Programming Language :: Python :: 3
Classifier: Programming Language :: Python :: 3.8
Classifier: Programming Language :: Python :: 3.9
Classifier: Programming Language :: Python :: 3.10
Classifier: Programming Language :: Python :: 3.11
Requires-Python: >=3.8
Requires-Dist: blake3>=1.0.5
Dynamic: author
Dynamic: requires-python
